DataframeProcessing/__init__.py
DataframeProcessing-0.0.1.dist-info/LICENSE.txt
DataframeProcessing-0.0.1.dist-info/METADATA
DataframeProcessing-0.0.1.dist-info/WHEEL
DataframeProcessing-0.0.1.dist-info/top_level.txt
DataframeProcessing-0.0.1.dist-info/RECORD
