Metadata-Version: 2.1
Name: DataframeProcessing
Version: 0.0.1
Summary: Handles NaN and Standardizes all values in a Dataframe
Home-page: https://github.com/KaranJani/PyPi-DataframeProcessing
Author: Karan Jani
License: UNKNOWN
Keywords: StandardScaler,fill na,pandas dataframe
Platform: UNKNOWN
Classifier: Programming Language :: Python :: 3
Classifier: License :: OSI Approved :: MIT License
Classifier: Operating System :: OS Independent
Requires-Python: >=3.6
License-File: LICENSE.txt
Requires-Dist: pandas
Requires-Dist: numpy
Requires-Dist: sklearn
